omni_split/__init__.py
omni_split/main.py
omni_split/omni_split.py
omni_split/test.py
omni_split/base/__init__.py
omni_split/base/chonkie_base.py
omni_split/base/chonkie_tokenizer.py
omni_split/base/chonkie_types.py
omni_split/base/md2json_list.py
omni_split/base/md_json_list2chunk.py
omni_split/base/native_text_split_utils4content2.py
omni_split/model/text_chunker_tokenizer/qwen_tokenizer.json
omni_split/sub_chunker/__init__.py
omni_split/sub_chunker/document_split.py
omni_split/sub_chunker/markdown_split.py
omni_split/sub_chunker/text_split.py
omni_split/utils/__init__.py
omni_split/utils/base_utils.py
omni_split/utils/download_test_doc.py
omni_split-0.0.1rc0.dist-info/licenses/LICENSE
omni_split-0.0.1rc0.dist-info/METADATA
omni_split-0.0.1rc0.dist-info/WHEEL
omni_split-0.0.1rc0.dist-info/top_level.txt
omni_split-0.0.1rc0.dist-info/RECORD
