Metadata-Version: 2.4
Name: omni_split
Version: 0.0.1rc0
Summary: A comprehensive document splitting toolkit
Home-page: https://github.com/dinobot22/omni_split
Author: dinobot22
Author-email: 2802701695yyb@gmail.com
Classifier: Programming Language :: Python :: 3
Classifier: License :: OSI Approved :: MIT License
Classifier: Operating System :: OS Independent
Requires-Python: >=3.7
License-File: LICENSE
Requires-Dist: mistletoe
Requires-Dist: transformers
Requires-Dist: markitdown[docx,pptx,xls,xlsx]
Requires-Dist: python-docx
Requires-Dist: loguru
Requires-Dist: wand
Dynamic: author
Dynamic: author-email
Dynamic: classifier
Dynamic: description
Dynamic: description-content-type
Dynamic: home-page
Dynamic: license-file
Dynamic: requires-dist
Dynamic: requires-python
Dynamic: summary
